TwilioToEmail/TwilioMail.py
TwilioToEmail/__init__.py
TwilioToEmail-0.0.7.dist-info/LICENSE.txt
TwilioToEmail-0.0.7.dist-info/METADATA
TwilioToEmail-0.0.7.dist-info/WHEEL
TwilioToEmail-0.0.7.dist-info/top_level.txt
TwilioToEmail-0.0.7.dist-info/RECORD
