Metadata-Version: 2.1
Name: TwilioToEmail
Version: 0.0.7
Summary: A middle man service that acts as a Twilio wrapper
Home-page: https://github.com/lowmoney/twilio_to_email
Author: Ruckshan Ratnam
Author-email: hendryratnam@gmail.com
License: UNKNOWN
Platform: UNKNOWN
Classifier: Programming Language :: Python :: 3
Classifier: License :: OSI Approved :: MIT License
Classifier: Operating System :: OS Independent
Requires-Python: >=3.6
Requires-Dist: requests
